Metadata-Version: 2.0
Name: olivia-django-cities-light
Version: 1.0.0
Summary: Simple alternative to django-cities
Home-page: https://github.com/nguyencg/django-cities-light.git
Author: phongtran
Author-email: phong.tran@paradox.ai
License: MIT
Keywords: django cities countries postal codes
Platform: UNKNOWN
Classifier: Development Status :: 5 - Production/Stable
Classifier: Environment :: Web Environment
Classifier: Framework :: Django
Classifier: Intended Audience :: Developers
Classifier: License :: OSI Approved :: MIT License
Classifier: Operating System :: OS Independent
Classifier: Programming Language :: Python
Classifier: Programming Language :: Python :: 2
Classifier: Programming Language :: Python :: 3
Classifier: Topic :: Internet :: WWW/HTTP
Classifier: Topic :: Software Development :: Libraries :: Python Modules
Requires-Dist: django-autoslug-iplweb (==1.9.4.dev0)
Requires-Dist: progressbar2 (>=3.6.0)
Requires-Dist: pytz
Requires-Dist: six
Requires-Dist: unidecode (>=0.04.13)
